chargame_2048/__init__.py
chargame_2048/__main__.py
chargame_2048/logic.py
chargame_2048/render.py
chargame_2048/util.py
util/__init__.py
util/dict_wrapper.py
util/resolve_argv.py
chargame_2048-0.0.4.dist-info/LICENSE.txt
chargame_2048-0.0.4.dist-info/METADATA
chargame_2048-0.0.4.dist-info/WHEEL
chargame_2048-0.0.4.dist-info/entry_points.txt
chargame_2048-0.0.4.dist-info/top_level.txt
chargame_2048-0.0.4.dist-info/RECORD
